pacflypy/__init__.py
pacflypy/pacflypy.py
pacflypy/command/__init__.py
pacflypy/command/command.py
pacflypy/control/__init__.py
pacflypy/control/control.py
pacflypy/exceptions/__init__.py
pacflypy/exceptions/exception.py
pacflypy/flytar/__init__.py
pacflypy/flytar/flytar.py
pacflypy/style/__init__.py
pacflypy/style/style.py
pacflypy/system/__init__.py
pacflypy/system/system.py
pacflypy-0.2.8.dist-info/METADATA
pacflypy-0.2.8.dist-info/WHEEL
pacflypy-0.2.8.dist-info/top_level.txt
pacflypy-0.2.8.dist-info/RECORD
