Metadata-Version: 2.1
Name: pacflypy
Version: 0.2.8
Summary: PacflyPy is a Special Python Module
Home-page: https://github.com/PacflyPy/PacflyPy
Author: PacflyPy
Author-email: PacflyPy <pacflypy@pacflypy.com>
Project-URL: Homepage, https://github.com/PacflyPy/PacflyPy
Classifier: Development Status :: 3 - Alpha
Classifier: License :: OSI Approved :: MIT License
Classifier: Programming Language :: Python :: 3.10
